ShynaAutomation/EmailAutomation.py
ShynaAutomation/NewsAutomation.py
ShynaAutomation/ShynaMasterNotify.py
ShynaAutomation/__init__.py
ShynaAutomation-0.1.39.dist-info/LICENSE
ShynaAutomation-0.1.39.dist-info/METADATA
ShynaAutomation-0.1.39.dist-info/WHEEL
ShynaAutomation-0.1.39.dist-info/top_level.txt
ShynaAutomation-0.1.39.dist-info/RECORD
