Metadata-Version: 2.1
Name: ShynaAutomation
Version: 0.1.39
Summary: Shyna Backend Functionality Package For Automation
Author: Shivam Sharma
Author-email: shivamsharma1913@gmail.com
License-File: LICENSE
Requires-Dist: ShynaTime
Requires-Dist: ShynaDatabase
Requires-Dist: ShynaProcess
Requires-Dist: imbox
Requires-Dist: beautifulsoup4
Requires-Dist: mysql-connector-python
Requires-Dist: nltk
Requires-Dist: setuptools
Requires-Dist: wheel
